odoo_utils/__init__.py
odoo_utils/main.py
odoo_utils-0.1.dev0.dist-info/LICENSE
odoo_utils-0.1.dev0.dist-info/METADATA
odoo_utils-0.1.dev0.dist-info/WHEEL
odoo_utils-0.1.dev0.dist-info/top_level.txt
odoo_utils-0.1.dev0.dist-info/RECORD
