Metadata-Version: 2.1
Name: odoo-utils
Version: 0.1.dev0
Summary: Project description
Home-page: https://github.com/voronind/odoo-utils
Author: Dmitry Voronin
Author-email: dimka665@gmail.com
License: MIT License
Platform: UNKNOWN
Classifier: License :: OSI Approved :: MIT License
Classifier: Programming Language :: Python :: 2.7
Classifier: Programming Language :: Python :: 3 :: Only
Classifier: Programming Language :: Python :: Implementation :: PyPy
Classifier: Intended Audience :: Developers
Classifier: Topic :: Software Development :: Libraries :: Python Modules
